doode/__init__.py
doode/__main__.py
doode/__version__.py
doode/doode.cp310-win_amd64.pyd
doode-0.48.3.data/data/README.md
doode-0.48.3.data/data/__version__.py
doode-0.48.3.dist-info/licenses/LICENSE
doode-0.48.3.dist-info/METADATA
doode-0.48.3.dist-info/WHEEL
doode-0.48.3.dist-info/entry_points.txt
doode-0.48.3.dist-info/top_level.txt
doode-0.48.3.dist-info/RECORD
