Metadata-Version: 2.4
Name: doode
Version: 0.48.3
Summary: Doode: DoodStream CLI, API Client, Url link Generator
Home-page: https://github.com/cumulus13/doode
Author: Hadi Cahyadi LD
Author-email: cumulus13@gmail.com
Maintainer: cumulus13 Team
Maintainer-email: cumulus13@gmail.com
License: GPL
Project-URL: Documentation, https://github.com/cumulus13/doode
Project-URL: Code, https://github.com/cumulus13/doode
Classifier: Development Status :: 5 - Production/Stable
Classifier: Intended Audience :: Developers
Classifier: License :: OSI Approved :: GNU General Public License (GPL)
Classifier: Operating System :: OS Independent
Classifier: Programming Language :: Python
Classifier: Programming Language :: Python :: 3
Classifier: Programming Language :: Python :: 3.8
Classifier: Programming Language :: Python :: 3.9
Classifier: Programming Language :: Python :: 3.10
Classifier: Programming Language :: Python :: 3.11
Requires-Python: >=3.8
License-File: LICENSE
Requires-Dist: rich>=13.0.0
Requires-Dist: bs4>=0.0.1
Requires-Dist: beautifulsoup4>=4.9.0
Requires-Dist: licface
Requires-Dist: clipboard>=0.0.4
Requires-Dist: requests
Requires-Dist: configset
Requires-Dist: idm
Dynamic: author
Dynamic: author-email
Dynamic: classifier
Dynamic: description
Dynamic: description-content-type
Dynamic: home-page
Dynamic: license
Dynamic: license-file
Dynamic: maintainer
Dynamic: maintainer-email
Dynamic: project-url
Dynamic: requires-dist
Dynamic: requires-python
Dynamic: summary
